common_hanzi/__init__.py
common_hanzi-0.1.dist-info/DESCRIPTION.rst
common_hanzi-0.1.dist-info/METADATA
common_hanzi-0.1.dist-info/RECORD
common_hanzi-0.1.dist-info/WHEEL
common_hanzi-0.1.dist-info/metadata.json
common_hanzi-0.1.dist-info/top_level.txt
