Metadata-Version: 2.0
Name: common-hanzi
Version: 0.1
Summary: Get common simplified Chinese characters (一级汉字和二级汉字)
Home-page: https://github.com/windtail/common_hanzi
Author: Luo Jiejun
Author-email: 6020100326ljj@163.com
License: Public domain
Platform: UNKNOWN
